Orange3_ImageAnalytics_DDA-0.5.3-py3.6-nspkg.pth
Orange3_ImageAnalytics_DDA-0.5.3.data/data/help/orange3-imageanalytics/.buildinfo
Orange3_ImageAnalytics_DDA-0.5.3.data/data/help/orange3-imageanalytics/Orange3ImageAnalyticsdoc.hhc
Orange3_ImageAnalytics_DDA-0.5.3.data/data/help/orange3-imageanalytics/Orange3ImageAnalyticsdoc.hhk
Orange3_ImageAnalytics_DDA-0.5.3.data/data/help/orange3-imageanalytics/Orange3ImageAnalyticsdoc.hhp
Orange3_ImageAnalytics_DDA-0.5.3.data/data/help/orange3-imageanalytics/Orange3ImageAnalyticsdoc.stp
Orange3_ImageAnalytics_DDA-0.5.3.data/data/help/orange3-imageanalytics/genindex.html
Orange3_ImageAnalytics_DDA-0.5.3.data/data/help/orange3-imageanalytics/index.html
Orange3_ImageAnalytics_DDA-0.5.3.data/data/help/orange3-imageanalytics/_static/basic.css
Orange3_ImageAnalytics_DDA-0.5.3.data/data/help/orange3-imageanalytics/_static/doctools.js
Orange3_ImageAnalytics_DDA-0.5.3.data/data/help/orange3-imageanalytics/_static/documentation_options.js
Orange3_ImageAnalytics_DDA-0.5.3.data/data/help/orange3-imageanalytics/_static/file.png
Orange3_ImageAnalytics_DDA-0.5.3.data/data/help/orange3-imageanalytics/_static/jquery-3.5.1.js
Orange3_ImageAnalytics_DDA-0.5.3.data/data/help/orange3-imageanalytics/_static/jquery.js
Orange3_ImageAnalytics_DDA-0.5.3.data/data/help/orange3-imageanalytics/_static/language_data.js
Orange3_ImageAnalytics_DDA-0.5.3.data/data/help/orange3-imageanalytics/_static/minus.png
Orange3_ImageAnalytics_DDA-0.5.3.data/data/help/orange3-imageanalytics/_static/nature.css
Orange3_ImageAnalytics_DDA-0.5.3.data/data/help/orange3-imageanalytics/_static/plus.png
Orange3_ImageAnalytics_DDA-0.5.3.data/data/help/orange3-imageanalytics/_static/pygments.css
Orange3_ImageAnalytics_DDA-0.5.3.data/data/help/orange3-imageanalytics/_static/searchtools.js
Orange3_ImageAnalytics_DDA-0.5.3.data/data/help/orange3-imageanalytics/_static/underscore-1.3.1.js
Orange3_ImageAnalytics_DDA-0.5.3.data/data/help/orange3-imageanalytics/_static/underscore.js
Orange3_ImageAnalytics_DDA-0.5.3.dist-info/LICENSE
Orange3_ImageAnalytics_DDA-0.5.3.dist-info/LICENSE.txt
Orange3_ImageAnalytics_DDA-0.5.3.dist-info/METADATA
Orange3_ImageAnalytics_DDA-0.5.3.dist-info/WHEEL
Orange3_ImageAnalytics_DDA-0.5.3.dist-info/entry_points.txt
Orange3_ImageAnalytics_DDA-0.5.3.dist-info/namespace_packages.txt
Orange3_ImageAnalytics_DDA-0.5.3.dist-info/top_level.txt
Orange3_ImageAnalytics_DDA-0.5.3.dist-info/RECORD
