Metadata-Version: 2.1
Name: Orange3-ImageAnalytics-DDA
Version: 0.5.3
Summary: Orange3 add-on for image data mining.
Home-page: http://orange.biolab.si/download
Author: Bioinformatics Laboratory, FRI UL
Author-email: contact@orange.biolab.si
License: GPL3+
Keywords: orange3 add-on,orange3-imageanalytics
Platform: UNKNOWN
Classifier: Development Status :: 1 - Planning
Classifier: Intended Audience :: Education
Classifier: Intended Audience :: Science/Research
Classifier: License :: OSI Approved :: GNU General Public License v3 or later (GPLv3+)
Classifier: Programming Language :: Python :: 3 :: Only
Requires-Dist: Orange3 (>=3.25.0)
Requires-Dist: cachecontrol
Requires-Dist: lockfile
Requires-Dist: ndf (>=0.1.4)
Requires-Dist: numpy (>=1.16.*)
Requires-Dist: pillow (>=6.2.0)
Requires-Dist: requests
Requires-Dist: scipy
Requires-Dist: tensorflow
